nbmetaclean/__init__.py
nbmetaclean/app_check.py
nbmetaclean/app_clean.py
nbmetaclean/check.py
nbmetaclean/clean.py
nbmetaclean/helpers.py
nbmetaclean/nb_types.py
nbmetaclean/version.py
nbmetaclean-0.1.4.dist-info/LICENSE
nbmetaclean-0.1.4.dist-info/METADATA
nbmetaclean-0.1.4.dist-info/WHEEL
nbmetaclean-0.1.4.dist-info/entry_points.txt
nbmetaclean-0.1.4.dist-info/top_level.txt
nbmetaclean-0.1.4.dist-info/RECORD
