Metadata-Version: 2.2
Name: nbmetaclean
Version: 0.1.4
Summary: Clean jupyter notebooks. Remove metadata and execution counts.
Home-page: https://github.com/ayasyrev/nbmetaclean
Author: Yasyrev Andrei
Author-email: a.yasyrev@gmail.com
License: apache2
Classifier: Programming Language :: Python :: 3.8
Classifier: Programming Language :: Python :: 3.9
Classifier: Programming Language :: Python :: 3.10
Classifier: Programming Language :: Python :: 3.11
Classifier: Programming Language :: Python :: 3.12
Classifier: Programming Language :: Python :: 3.13
Classifier: License :: OSI Approved :: Apache Software License
Classifier: Operating System :: OS Independent
Requires-Python: >=3.8
License-File: LICENSE
Provides-Extra: test
Provides-Extra: dev
Dynamic: provides-extra
